capsrv/__init__.py
capsrv/__main__.py
capsrv/server.py
capsrv-0.0.170.dist-info/LICENSE
capsrv-0.0.170.dist-info/METADATA
capsrv-0.0.170.dist-info/WHEEL
capsrv-0.0.170.dist-info/top_level.txt
capsrv-0.0.170.dist-info/RECORD
