Metadata-Version: 2.1
Name: capsrv
Version: 0.0.170
Summary: Hack the Box Team Support Services
License-File: LICENSE
Requires-Dist: flask
Provides-Extra: rel
Requires-Dist: twine ; extra == 'rel'
Provides-Extra: test
Requires-Dist: coverage ; extra == 'test'
Requires-Dist: pytest ; extra == 'test'
